LICENSE.txt
MANIFEST.in
README.rst
setup.cfg
setup.py
activityio/__init__.py
activityio/tools.py
activityio/tools_test.py
activityio.egg-info/PKG-INFO
activityio.egg-info/SOURCES.txt
activityio.egg-info/dependency_links.txt
activityio.egg-info/entry_points.txt
activityio.egg-info/requires.txt
activityio.egg-info/top_level.txt
activityio/_types/__init__.py
activityio/_types/activitydata.py
activityio/_types/base.py
activityio/_types/columns.py
activityio/_util/__init__.py
activityio/_util/cli.py
activityio/_util/drydoc.py
activityio/_util/exceptions.py
activityio/_util/misc.py
activityio/_util/reader.py
activityio/_util/xml_reading.py
activityio/_util/xml_reading_test.py
activityio/fit/__init__.py
activityio/fit/_profile.py
activityio/fit/_protocol.py
activityio/fit/_reading.py
activityio/gpx/__init__.py
activityio/gpx/_reading.py
activityio/pwx/__init__.py
activityio/pwx/_reading.py
activityio/srm/__init__.py
activityio/srm/_reading.py
activityio/tcx/__init__.py
activityio/tcx/_reading.py