Metadata-Version: 1.1
Name: activityio
Version: 0.0.3
Summary: Exercise data handling library
Home-page: https://github.com/jmackie4/activityio
Author: Jordan Mackie
Author-email: jmackie@protonmail.com
License: MIT
Keywords: exercise cycling running garmin data
Platform: UNKNOWN
Classifier: Development Status :: 3 - Alpha
Classifier: Intended Audience :: Science/Research
Classifier: Topic :: Scientific/Engineering :: Medical Science Apps.
Classifier: License :: OSI Approved :: MIT License
Classifier: Programming Language :: Python :: 3.5
